organizador/__init__.py
organizador/aj_progressB.py
organizador/main.py
organizador-0.1.1.dist-info/LICENSE
organizador-0.1.1.dist-info/METADATA
organizador-0.1.1.dist-info/WHEEL
organizador-0.1.1.dist-info/top_level.txt
organizador-0.1.1.dist-info/RECORD
