Metadata-Version: 2.1
Name: organizador
Version: 0.1.1
Summary: Organiza archivos en carpetas teniendo como referencia las similitudes en sus nombres.
Home-page: https://github.com/Armando-J/organizador
Author: Armando J
License: UNKNOWN
Platform: UNKNOWN
License-File: LICENSE
